cbbuild/__init__.py
cbbuild/manifest/__init__.py
cbbuild/manifest/info.py
cbbuild/manifest/parse.py
cbbuild_manifest-0.7.0.dist-info/METADATA
cbbuild_manifest-0.7.0.dist-info/WHEEL
cbbuild_manifest-0.7.0.dist-info/RECORD
