Metadata-Version: 2.3
Name: cbbuild-manifest
Version: 0.7.0
Summary: Couchbase Build Team manifest package
Author-email: Couchbase Build Team <build-team@couchbase.com>
License: Apache License, Version 2.0
Requires-Python: <4,>=3.6
Requires-Dist: lxml>=3.8.0
